<?xml version="1.0"?>
<data>
  <races>
    <race name="Human">
      <talents>
        <talent>Dunkel Sicht</talent>
        <talent>Stupid</talent>
        <talent>Defensive Training</talent>
      </talents>
    </race>
    <race name="Ork">
      <talents>
        <talent>Hyper Intellegent</talent>
      </talents>
    </race>
  </races>
  <talents>
    <talent name="Dunkel Sicht">Verleit Sicht im Dunklen</talent>
    <talent name="Defensive Training">Training im defensiven Kampfstil</talent>
    <talent name="Stupid">Meiser der Lufthirn Technik</talent>
    <talent name="Hyper Intellegent">Meister der heißen Lufthirn Technik</talent>
  </talents>
</data>
